doom/__init__.py
inspect/__init__.py
muis/__init__.py
toets/__init__.py
gpilot-0.0.1.dist-info/LICENSE.txt
gpilot-0.0.1.dist-info/METADATA
gpilot-0.0.1.dist-info/WHEEL
gpilot-0.0.1.dist-info/entry_points.txt
gpilot-0.0.1.dist-info/top_level.txt
gpilot-0.0.1.dist-info/RECORD
