Metadata-Version: 2.1
Name: gpilot
Version: 0.0.1
Summary: AI Journalist
Author-email: Yilmaz Mustafa <dev@mail.be>
License: Copyright (c) 2016 The Python Packaging Authority (PyPA)
Project-URL: Homepage, https://www.codesapien.be/gpilot/
Project-URL: Bug Reports, https://github.com/codesapienbe/gpilot/issues
Project-URL: Funding, https://donate.pypi.org
Project-URL: Say Thanks!, http://saythanks.io/to/gpilot
Project-URL: Source, https://github.com/codesapienbe/gpilot
Keywords: gpilot,setuptools,development,ai journalist,machine learning,artificial intelligence
Classifier: Development Status :: 3 - Alpha
Classifier: Intended Audience :: Developers
Classifier: Topic :: Software Development :: Build Tools
Classifier: License :: OSI Approved :: MIT License
Classifier: Programming Language :: Python :: 3.9
Classifier: Programming Language :: Python :: 3.10
Classifier: Programming Language :: Python :: 3.11
Classifier: Programming Language :: Python :: 3 :: Only
Requires-Python: >=3.9
License-File: LICENSE.txt
Requires-Dist: install
Requires-Dist: requests
Requires-Dist: setuptools
Requires-Dist: build
Requires-Dist: black
Requires-Dist: coverage
Requires-Dist: flake8
Requires-Dist: pep8-naming
Requires-Dist: pytest
Requires-Dist: pytest-cov
Requires-Dist: pytest-mock
Requires-Dist: pytest-profiling
Requires-Dist: wheel
Requires-Dist: twine
Requires-Dist: pylint
Requires-Dist: autopep8
Requires-Dist: pyinstaller
Requires-Dist: opencv-python
Requires-Dist: mediapipe
Requires-Dist: cvzone
Requires-Dist: pandas
Requires-Dist: python-dotenv
Requires-Dist: kivy[dev]
Requires-Dist: keras
Requires-Dist: jupyter
Requires-Dist: jupyterlab
Requires-Dist: jupyterlab-code-formatter
Requires-Dist: jupyterlab-git
Requires-Dist: jupyterlab-lsp
Requires-Dist: pynput
Requires-Dist: gymnasium
Requires-Dist: tensorflow
Requires-Dist: pika
Requires-Dist: vizdoom
Requires-Dist: vizdoom[gym]
Provides-Extra: dev
Requires-Dist: check-manifest ; extra == 'dev'
Provides-Extra: test
Requires-Dist: coverage ; extra == 'test'
